klp_commons/.DS_Store
klp_commons/__init__.py
klp_commons/controllers/.DS_Store
klp_commons/controllers/__init__.py
klp_commons/controllers/controller_dynamodb.py
klp_commons/controllers/controller_mlflow.py
klp_commons/controllers/controller_mongodb.py
klp_commons/controllers/controller_postgresdb.py
klp_commons/controllers/controller_redshift.py
klp_commons/cryptools/.DS_Store
klp_commons/cryptools/__init__.py
klp_commons/cryptools/cryptology.py
klp_commons/datadict/.DS_Store
klp_commons/datadict/__init__.py
klp_commons/datadict/struct_dicts.py
klp_commons/datefinder/__init__.py
klp_commons/datefinder/constants.py
klp_commons/datefinder/date_fragment.py
klp_commons/log/.DS_Store
klp_commons/log/__init__.py
klp_commons/log/log.py
klp_commons/log/structuredMessage.py
klp_commons/places/__init__.py
klp_commons/places/apis.py
klp_commons/scripts/.DS_Store
klp_commons/scripts/__init__.py
klp_commons/scripts/detect_recurrency.py
klp_commons/scripts/get_send_kw_group.py
klp_commons/scripts/ingest_dwh.py
klp_commons/scripts/summary.py
klp_commons/streaming/.DS_Store
klp_commons/streaming/__init__.py
klp_commons/streaming/consumer.py
klp_commons/streaming/producer.py
klp_commons/streaming/topics.log
klp_commons/streaming/topics.py
klp_commons/utils/.DS_Store
klp_commons/utils/__init__.py
klp_commons/utils/utils.py
klp_commons-0.0.69.dist-info/LICENSE
klp_commons-0.0.69.dist-info/WHEEL
klp_commons-0.0.69.dist-info/METADATA
klp_commons-0.0.69.dist-info/RECORD
