Metadata-Version: 2.1
Name: klp-commons
Version: 0.0.69
Summary: Modulo Commons del ecosistema Kloop. Contiene los modulos de uso común para los paquetes 
Author-email: Omar Santa Cruz <omar.castellanos@kolpp.mx>
Classifier: License :: OSI Approved :: MIT License
Project-URL: Home, https://gitlab.com/klopp1/backend/microservices/commons
